MangaDexPy/__init__.py
MangaDexPy/author.py
MangaDexPy/chapter.py
MangaDexPy/cover.py
MangaDexPy/downloader.py
MangaDexPy/group.py
MangaDexPy/manga.py
MangaDexPy/network.py
MangaDexPy/search.py
MangaDexPy/user.py
MangaDex.py-2.0.10.dist-info/LICENSE.md
MangaDex.py-2.0.10.dist-info/METADATA
MangaDex.py-2.0.10.dist-info/WHEEL
MangaDex.py-2.0.10.dist-info/top_level.txt
MangaDex.py-2.0.10.dist-info/RECORD
