Metadata-Version: 2.1
Name: MangaDex.py
Version: 2.0.10
Summary: An API wrapper for the MangaDexAPIv5.
Home-page: https://github.com/Proxymiity/MangaDex.py
Author: Proxymiity
Author-email: dev@ayaya.red
License: MIT
Download-URL: https://github.com/Proxymiity/MangaDex.py/releases
Platform: UNKNOWN
Classifier: License :: OSI Approved :: MIT License
Classifier: Operating System :: OS Independent
Classifier: Programming Language :: Python :: 3.6
Classifier: Programming Language :: Python :: 3.7
Classifier: Programming Language :: Python :: 3.8
Classifier: Programming Language :: Python :: 3.9
Classifier: Programming Language :: Python :: 3.10
Classifier: Topic :: Internet
Classifier: Topic :: Software Development :: Libraries
Classifier: Topic :: Software Development :: Libraries :: Python Modules
Classifier: Topic :: Utilities
Classifier: Intended Audience :: Developers
Requires-Python: >=3.6
License-File: LICENSE.md
